{
"type": "FeatureCollection",
"name": "circus",
"crs": { "type": "name", "properties": { "name": "urn:ogc:def:crs:OGC:1.3:CRS84" } },
"features": [
{ "type": "Feature", "properties": { "Наименование": "Кемеровский государственный цирк", "Описание": null, "Рубрики": "Цирк; Интересные здания", "Адрес": "проспект Ленина, 56", "Комментарий к адресу": null, "Почтовый индекс": 650066, "Микрорайон": null, "Район": "Центральный район", "Город": "Кемерово", "Округ": "Кемеровский городской округ", "Регион": "Кемеровская область — Кузбасс", "Страна": "Россия", "Часы работы": "Пн: 10:00-19:00; Вт: 10:00-19:00; Ср: 10:00-19:00; Чт: 10:00-19:00; Пт: 10:00-19:00; Сб: 10:00-19:00; Вс: 10:00-19:00 (администрация: пн-пт 8:30-17:30)", "Часовой пояс": "+07:00", "Рейтинг": 3.2, "Количество отзывов": 162, "Телефон": "83842780877 (касса)", "Веб-сайт": "http://circus-kemerovo.ru", "ВКонтакте": "https://vk.com/circus_kemerovo", "Широта": 55.345195, "Долгота": 86.099635, "2GIS URL": "https://2gis.com/firm/704215722755213" }, "geometry": { "type": "Point", "coordinates": [ 86.099635, 55.345195 ] } }
]
}
