{
"type": "FeatureCollection",
"name": "emergency",
"crs": { "type": "name", "properties": { "name": "urn:ogc:def:crs:OGC:1.3:CRS84" } },
"features": [
{ "type": "Feature", "properties": { "Наименование": "Кузбасская клиническая станция скорой медицинской помощи", "Описание": "правобережная подстанция", "Рубрики": "Скорая медицинская помощь", "Адрес": "улица Рутгерса, 39а", "Комментарий к адресу": null, "Почтовый индекс": 650044, "Микрорайон": null, "Район": "Рудничный район", "Город": "Кемерово", "Округ": "Кемеровский городской округ", "Регион": "Кемеровская область — Кузбасс", "Страна": "Россия", "Часы работы": "Пн: 00:00-24:00; Вт: 00:00-24:00; Ср: 00:00-24:00; Чт: 00:00-24:00; Пт: 00:00-24:00; Сб: 00:00-24:00; Вс: 00:00-24:00", "Часовой пояс": "+07:00", "Рейтинг": 5.0, "Количество отзывов": 3, "Телефон 1": "83842642206", "Телефон 2": null, "Телефон 3": null, "Веб-сайт": null, "ВКонтакте": null, "Широта": 55.383595, "Долгота": 86.082724, "2GIS URL": "https://2gis.com/firm/704215723259856" }, "geometry": { "type": "Point", "coordinates": [ 86.082724, 55.383595 ] } },
{ "type": "Feature", "properties": { "Наименование": "Кузбасская клиническая станция скорой медицинской помощи", "Описание": "главная подстанция", "Рубрики": "Скорая медицинская помощь", "Адрес": "Волгоградская, 39", "Комментарий к адресу": null, "Почтовый индекс": 650036, "Микрорайон": null, "Район": "Ленинский район", "Город": "Кемерово", "Округ": "Кемеровский городской округ", "Регион": "Кемеровская область — Кузбасс", "Страна": "Россия", "Часы работы": "Пн: 08:00-12:00, 12:30-16:00; Вт: 08:00-12:00, 12:30-16:00; Ср: 08:00-12:00, 12:30-16:00; Чт: 08:00-12:00, 12:30-16:00; Пт: 08:00-12:00, 12:30-14:00", "Часовой пояс": "+07:00", "Рейтинг": 3.0, "Количество отзывов": 22, "Телефон 1": "83842310003 (справочная)", "Телефон 2": "83842310005 (круглосуточный)", "Телефон 3": "83842549879 (круглосуточный)", "Веб-сайт": null, "ВКонтакте": "https://vk.com/kkssmp", "Широта": 55.334555, "Долгота": 86.157083, "2GIS URL": "https://2gis.com/firm/704215722983851" }, "geometry": { "type": "Point", "coordinates": [ 86.157083, 55.334555 ] } },
{ "type": "Feature", "properties": { "Наименование": "Кузбасская клиническая станция скорой медицинской помощи", "Описание": "центральная подстанция", "Рубрики": "Скорая медицинская помощь", "Адрес": "Николая Островского, 24", "Комментарий к адресу": null, "Почтовый индекс": 650000, "Микрорайон": null, "Район": "Центральный район", "Город": "Кемерово", "Округ": "Кемеровский городской округ", "Регион": "Кемеровская область — Кузбасс", "Страна": "Россия", "Часы работы": "Пн: 00:00-24:00; Вт: 00:00-24:00; Ср: 00:00-24:00; Чт: 00:00-24:00; Пт: 00:00-24:00; Сб: 00:00-24:00; Вс: 00:00-24:00", "Часовой пояс": "+07:00", "Рейтинг": 3.0, "Количество отзывов": 4, "Телефон 1": "83842368105", "Телефон 2": null, "Телефон 3": null, "Веб-сайт": null, "ВКонтакте": null, "Широта": 55.359918, "Долгота": 86.082796, "2GIS URL": "https://2gis.com/firm/704215723259855" }, "geometry": { "type": "Point", "coordinates": [ 86.082796, 55.359918 ] } }
]
}
